CAPEsolo/__init__.py
CAPEsolo/analysis_conf.default
CAPEsolo/analyzer.py
CAPEsolo/bin/autoit3.exe
CAPEsolo/bin/file.exe
CAPEsolo/bin/loader.exe
CAPEsolo/bin/loader_x64.exe
CAPEsolo/bin/PPLinject.exe
CAPEsolo/bin/PPLinject64.exe
CAPEsolo/bin/psexec.exe
CAPEsolo/bin/signtool.exe
CAPEsolo/cape_logo.png
CAPEsolo/capelib/__init__.py
CAPEsolo/capelib/behavior.py
CAPEsolo/capelib/cape_utils.py
CAPEsolo/capelib/cmdconsts.py
CAPEsolo/capelib/logtbl.py
CAPEsolo/capelib/netlog.py
CAPEsolo/capelib/objects.py
CAPEsolo/capelib/parse_pe.py
CAPEsolo/capelib/path_utils.py
CAPEsolo/capelib/resultserver.py
CAPEsolo/capelib/signatures.py
CAPEsolo/capelib/url_validate.py
CAPEsolo/capelib/utils.py
CAPEsolo/capelib/utils_dicts.py
CAPEsolo/capelib/utils_pretty_print_funcs.py
CAPEsolo/capelib/yaralib.py
CAPEsolo/capesolo.ico
CAPEsolo/capesolo.png
CAPEsolo/cfg.ini
CAPEsolo/classes/__init__.py
CAPEsolo/classes/behavior_panel.py
CAPEsolo/classes/configs_panel.py
CAPEsolo/classes/custom_grid.py
CAPEsolo/classes/debug_console.py
CAPEsolo/classes/debug_controls.py
CAPEsolo/classes/debug_pipe.py
CAPEsolo/classes/debugger_panel.py
CAPEsolo/classes/hexview_window.py
CAPEsolo/classes/json_report.py
CAPEsolo/classes/key_event.py
CAPEsolo/classes/logger_window.py
CAPEsolo/classes/main_frame.py
CAPEsolo/classes/patch_assembler.py
CAPEsolo/classes/patch_dialog.py
CAPEsolo/classes/patch_models.py
CAPEsolo/classes/payloads_panel.py
CAPEsolo/classes/pe_window.py
CAPEsolo/classes/process_yara.py
CAPEsolo/classes/search_dialog.py
CAPEsolo/classes/signatures_panel.py
CAPEsolo/classes/splash_screen.py
CAPEsolo/classes/start_panel.py
CAPEsolo/classes/strings_panel.py
CAPEsolo/classes/target_info.py
CAPEsolo/classes/timer_window.py
CAPEsolo/classes/yara_panel.py
CAPEsolo/cli.py
CAPEsolo/data/__init__.py
CAPEsolo/data/msix.ps1
CAPEsolo/data/safelist/__init__.py
CAPEsolo/data/safelist/disposable_domain_list.txt
CAPEsolo/data/safelist/domains.py
CAPEsolo/data/safelist/replacepatterns.py
capesolo-0.5.9.dist-info/entry_points.txt
capesolo-0.5.9.dist-info/METADATA
capesolo-0.5.9.dist-info/WHEEL
capesolo-0.5.9.dist-info/RECORD
