Metadata-Version: 2.3
Name: CAPEsolo
Version: 0.5.9
Summary: Standalone CAPEMON
Author: enzok
Author-email: 7831008+enzok@users.noreply.github.com
Requires-Python: >=3.10,<3.13
Classifier: Programming Language :: Python :: 3
Classifier: Programming Language :: Python :: 3.10
Classifier: Programming Language :: Python :: 3.11
Classifier: Programming Language :: Python :: 3.12
Requires-Dist: SFlock2 (>=0.3.79,<0.4.0)
Requires-Dist: bs2json (>=0.1.2,<0.2.0)
Requires-Dist: bson (>=0.5.10,<0.6.0)
Requires-Dist: cape-parsers (==0.1.49)
Requires-Dist: cryptography (>=45.0.7,<46.0.0)
Requires-Dist: distorm3s (==3.5.4)
Requires-Dist: dnspython (>=2.6.1,<3.0.0)
Requires-Dist: gevent (>=25.8.2,<26.0.0)
Requires-Dist: greenlet (>=3.2.4,<4.0.0)
Requires-Dist: keystone-engine (>=0.9.2,<0.10.0)
Requires-Dist: pefile (>=2024.8.26,<2025.0.0)
Requires-Dist: poetry-core (>=2.1.3,<3.0.0)
Requires-Dist: pytest (>=8.4.1,<9.0.0)
Requires-Dist: pywin32 (>=311,<312)
Requires-Dist: requests (>=2.32.5,<3.0.0)
Requires-Dist: ruff (==0.12.11)
Requires-Dist: setuptools (==80.9.0)
Requires-Dist: tldextract (>=5.3.0,<6.0.0)
Requires-Dist: typing-extensions (==4.15.0)
Requires-Dist: wxpython (>=4.2.3,<5.0.0)
Requires-Dist: yara-python (>=4.5.4,<5.0.0)
